{
  "descriptionHash": "4B9B58813AAC99EEB6FAF04D4419A08723F48DFFC118FCF162F0B4075DA0554B017E5BB5FC2594691D7D7C01FAFC519CCC86CEE1E8283DD753D9FD16B0187784",
  "descriptionLocation": "../../fixed.json",
  "lockFileVersion": "1.0.0",
  "kiotaVersion": "1.31.1",
  "clientClassName": "CoinbaseCdpOpenApiClient",
  "typeAccessModifier": "Public",
  "clientNamespaceName": "Soenneker.Coinbase.OpenApiClients.Cdp",
  "language": "CSharp",
  "usesBackingStore": false,
  "excludeBackwardCompatible": true,
  "includeAdditionalData": true,
  "disableSSLValidation": false,
  "serializers": [
    "Microsoft.Kiota.Serialization.Json.JsonSerializationWriterFactory",
    "Microsoft.Kiota.Serialization.Text.TextSerializationWriterFactory",
    "Microsoft.Kiota.Serialization.Form.FormSerializationWriterFactory",
    "Microsoft.Kiota.Serialization.Multipart.MultipartSerializationWriterFactory"
  ],
  "deserializers": [
    "Microsoft.Kiota.Serialization.Json.JsonParseNodeFactory",
    "Microsoft.Kiota.Serialization.Text.TextParseNodeFactory",
    "Microsoft.Kiota.Serialization.Form.FormParseNodeFactory"
  ],
  "structuredMimeTypes": [
    "application/json",
    "text/plain;q=0.9",
    "application/x-www-form-urlencoded;q=0.2",
    "multipart/form-data;q=0.1"
  ],
  "includePatterns": [],
  "excludePatterns": [],
  "disabledValidationRules": []
}